geojikuu/aggregation/point_aggregators.py
geojikuu/descriptives/spacetime_distribution.py
geojikuu/descriptives/spatial_distribution.py
geojikuu/hypothesis_testing/autocorrelation.py
geojikuu/hypothesis_testing/hot_spot_analysis.py
geojikuu/preprocessing/conversion_tools.py
geojikuu/preprocessing/normalisation.py
geojikuu/preprocessing/projection.py
geojikuu-0.27.55.dist-info/METADATA
geojikuu-0.27.55.dist-info/WHEEL
geojikuu-0.27.55.dist-info/licenses/LICENSE.txt
geojikuu-0.27.55.dist-info/RECORD
