Metadata-Version: 2.4
Name: GeoJikuu
Version: 0.27.55
Summary: GeoJikuu is a Python library for analysing geographical data that contains both spatial and spatiotemporal variables.
Project-URL: Homepage, https://github.com/kainedusher/GeoJikuu
Author-email: Kaine Usher <kaine.usher1@gmail.com>
License-File: LICENSE.txt
Classifier: License :: OSI Approved :: Apache Software License
Classifier: Operating System :: OS Independent
Classifier: Programming Language :: Python :: 3
Requires-Python: >=3.8
Requires-Dist: numpy>=1.25.2
Requires-Dist: pandas>=2.0.3
Requires-Dist: pyproj>=3.6.0
